xpinyin/Mandarin.dat
xpinyin/__init__.py
xpinyin/combs.py
xpinyin-0.7.7.dist-info/LICENSE
xpinyin-0.7.7.dist-info/METADATA
xpinyin-0.7.7.dist-info/WHEEL
xpinyin-0.7.7.dist-info/top_level.txt
xpinyin-0.7.7.dist-info/RECORD
